extractcode/NOTICE
extractcode/__init__.py
extractcode/api.py
extractcode/archive.py
extractcode/cli.py
extractcode/extract.py
extractcode/libarchive2.py
extractcode/patch.py
extractcode/sevenzip.py
extractcode/uncompress.py
extractcode/vmimage.py
extractcode-31.0.0.dist-info/AUTHORS.rst
extractcode-31.0.0.dist-info/CHANGELOG.rst
extractcode-31.0.0.dist-info/CODE_OF_CONDUCT.rst
extractcode-31.0.0.dist-info/METADATA
extractcode-31.0.0.dist-info/NOTICE
extractcode-31.0.0.dist-info/WHEEL
extractcode-31.0.0.dist-info/apache-2.0.LICENSE
extractcode-31.0.0.dist-info/entry_points.txt
extractcode-31.0.0.dist-info/top_level.txt
extractcode-31.0.0.dist-info/RECORD
