Metadata-Version: 2.1
Name: extractcode
Version: 31.0.0
Summary: A mostly universal archive extractor using 7zip, libarchive and the Python standard library for reliable archive extraction.
Home-page: https://github.com/nexB/extractcode
Author: nexB. Inc. and others
Author-email: info@aboutcode.org
License: Apache-2.0
Keywords: utilities,archive,extraction,libarchive,7zip,7z,gzip,bzip2,xz,lzma,lz4,lzip,zstd,Z,tar,xar,ar,cpio,vmdk,qcow2,vhd,iso,deb,cab,rpm,patch,scancode-toolkit
Platform: UNKNOWN
Classifier: Development Status :: 5 - Production/Stable
Classifier: Intended Audience :: Developers
Classifier: Programming Language :: Python :: 3
Classifier: Programming Language :: Python :: 3 :: Only
Classifier: Programming Language :: Python :: 3.6
Classifier: Programming Language :: Python :: 3.7
Classifier: Programming Language :: Python :: 3.8
Classifier: Programming Language :: Python :: 3.9
Classifier: Programming Language :: Python :: 3.10
Classifier: Topic :: Software Development
Classifier: Topic :: Utilities
Requires-Python: >=3.6.*
Provides-Extra: full
Provides-Extra: patch
Provides-Extra: testing
Provides-Extra: docs
License-File: apache-2.0.LICENSE
License-File: NOTICE
License-File: AUTHORS.rst
License-File: CHANGELOG.rst
License-File: CODE_OF_CONDUCT.rst
